includes/__init__.py
includes/bot.py
includes/filereader.py
includes/scan.py
includes/writefile.py
utils/__init__.py
utils/configure.py
utils/const.py
utils/helpers.py
vuln-1.1.dist-info/METADATA
vuln-1.1.dist-info/WHEEL
vuln-1.1.dist-info/entry_points.txt
vuln-1.1.dist-info/top_level.txt
vuln-1.1.dist-info/RECORD
