Metadata-Version: 2.1
Name: vuln
Version: 1.1
Requires-Dist: click
Requires-Dist: pyyaml
Requires-Dist: requests
